winrt/_winrt_microsoft_windows_management_deployment.cp313-win32.pyd
winrt/_winrt_microsoft_windows_management_deployment.pyi
winrt/microsoft/windows/management/deployment/__init__.py
winrt/microsoft/windows/management/deployment/py.typed
winrt_Microsoft.Windows.Management.Deployment-2.3.0.dist-info/METADATA
winrt_Microsoft.Windows.Management.Deployment-2.3.0.dist-info/WHEEL
winrt_Microsoft.Windows.Management.Deployment-2.3.0.dist-info/top_level.txt
winrt_Microsoft.Windows.Management.Deployment-2.3.0.dist-info/RECORD
